samaraenergo/__init__.py
samaraenergo/calc/__init__.py
samaraenergo/calc/__main__.py
samaraenergo-0.2.25.dist-info/METADATA
samaraenergo-0.2.25.dist-info/WHEEL
samaraenergo-0.2.25.dist-info/RECORD
