Metadata-Version: 2.1
Name: samaraenergo
Version: 0.2.25
Summary: Клиент электросбытовой компании СамараЭнерго
Author: Sergey V. DUDANOV
Author-email: sergey.dudanov@gmail.com
Requires-Python: >=3.12,<3.14
Classifier: Programming Language :: Python :: 3
Classifier: Programming Language :: Python :: 3.12
Classifier: Programming Language :: Python :: 3.13
Requires-Dist: aiohttp (>=3.11)
